progressbar/__init__.py
progressbar/progresstrackingbar.py
progresstrackingbar-0.1.dist-info/METADATA
progresstrackingbar-0.1.dist-info/WHEEL
progresstrackingbar-0.1.dist-info/top_level.txt
progresstrackingbar-0.1.dist-info/RECORD
